frontegg_ai_sdk/__init__.py
frontegg_ai_sdk/core/__init__.py
frontegg_ai_sdk/core/client.py
frontegg_ai_sdk/core/client_utils.py
frontegg_ai_sdk/core/config.py
frontegg_ai_sdk/core/enums.py
frontegg_ai_sdk/core/httpTransport.py
frontegg_ai_sdk/core/logger.py
frontegg_ai_sdk-1.0.0.dist-info/licenses/LICENSE.md
frontegg_ai_sdk-1.0.0.dist-info/METADATA
frontegg_ai_sdk-1.0.0.dist-info/WHEEL
frontegg_ai_sdk-1.0.0.dist-info/top_level.txt
frontegg_ai_sdk-1.0.0.dist-info/RECORD
