Metadata-Version: 2.4
Name: frontegg-ai-sdk
Version: 1.0.0
Summary: A Python SDK for interacting with Frontegg AI Agents.
Home-page: https://github.com/frontegg/frontegg-ai-python-sdk
Author: Frontegg
Author-email: support@frontegg.com
License-File: LICENSE.md
Requires-Dist: requests
Requires-Dist: httpx
Requires-Dist: anyio
Requires-Dist: httpx-sse
Requires-Dist: pydantic
Requires-Dist: mcp
Requires-Dist: crewai[tools]>=0.5.0
Requires-Dist: mcpadapt>=0.1.3
Requires-Dist: nest-asyncio
Dynamic: author
Dynamic: author-email
Dynamic: description
Dynamic: description-content-type
Dynamic: home-page
Dynamic: license-file
Dynamic: requires-dist
Dynamic: summary
